flexclient/Common.py
flexclient/DataHandler.py
flexclient/LAN.py
flexclient/Panafall.py
flexclient/Radio.py
flexclient/RxRemoteAudioStream.py
flexclient/Slice.py
flexclient/SmartLink.py
flexclient/Vita.py
flexclient/__init__.py
flexclient-0.1.dist-info/LICENSE.txt
flexclient-0.1.dist-info/METADATA
flexclient-0.1.dist-info/WHEEL
flexclient-0.1.dist-info/top_level.txt
flexclient-0.1.dist-info/RECORD
