Metadata-Version: 2.1
Name: flexclient
Version: 0.1
Summary: Python client API for the FLEX 6000 series radios
Home-page: https://github.com/phase4ground/flexclient
Author: Open Research Institute
Author-email: steve@conklinhouse.com
License: GPL
Project-URL: Bug Tracker, https://github.com/phase4ground/flexclient/issues
Platform: UNKNOWN
Classifier: Development Status :: 2 - Pre-Alpha
Classifier: Programming Language :: Python :: 3
Classifier: License :: OSI Approved :: GNU General Public License v3 or later (GPLv3+)
Classifier: Operating System :: OS Independent
Requires-Python: >=3.6
License-File: LICENSE.txt
Requires-Dist: selenium
